.coveragerc
AUTHORS.rst
CHANGES.rst
LICENSE.txt
README.rst
requirements.txt
setup.cfg
setup.py
test-requirements.txt
ddpuk/__init__.py
ddpuk/download.py
ddpuk.egg-info/PKG-INFO
ddpuk.egg-info/SOURCES.txt
ddpuk.egg-info/dependency_links.txt
ddpuk.egg-info/entry_points.txt
ddpuk.egg-info/not-zip-safe
ddpuk.egg-info/requires.txt
ddpuk.egg-info/top_level.txt
docs/Makefile
docs/authors.rst
docs/changes.rst
docs/conf.py
docs/index.rst
docs/license.rst
docs/_static/.gitignore
tests/conftest.py
tests/test_skeleton.py