Metadata-Version: 1.0
Name: ddpuk
Version: 0.0.1
Summary: data.parliament.uk for Humans
Home-page: https://ddpy.readthedocs.org
Author: Florian Rathgeber
Author-email: florian.rathgeber@gmail.com
License: mit
Platform: UNKNOWN
